actinia_tiling_plugin/__init__.py
actinia_tiling_plugin/endpoints.py
actinia_tiling_plugin/wsgi.py
actinia_tiling_plugin/api/__init__.py
actinia_tiling_plugin/api/merge_list.py
actinia_tiling_plugin/api/tiling_list.py
actinia_tiling_plugin/api/merge/__init__.py
actinia_tiling_plugin/api/merge/patch_merge.py
actinia_tiling_plugin/api/tiling/__init__.py
actinia_tiling_plugin/api/tiling/tiling_grid.py
actinia_tiling_plugin/apidocs/__init__.py
actinia_tiling_plugin/apidocs/merge.py
actinia_tiling_plugin/apidocs/tiling.py
actinia_tiling_plugin/core/__init__.py
actinia_tiling_plugin/models/__init__.py
actinia_tiling_plugin/models/response_models/__init__.py
actinia_tiling_plugin/models/response_models/general.py
actinia_tiling_plugin/models/response_models/merge.py
actinia_tiling_plugin/models/response_models/tiling.py
actinia_tiling_plugin/resources/__init__.py
actinia_tiling_plugin/resources/config.py
actinia_tiling_plugin/resources/logging.py
actinia_tiling_plugin/resources/processes.py
actinia_tiling_plugin/resources/templating.py
actinia_tiling_plugin/templates/__init__.py
actinia_tiling_plugin/templates/pc_create_grid.json
actinia_tiling_plugin/templates/pc_delete_vector.json
actinia_tiling_plugin/templates/pc_extract_grid.json
actinia_tiling_plugin/templates/patch/__init__.py
actinia_tiling_plugin/templates/patch/pc_patch_raster.json
actinia_tiling_plugin/templates/patch/pc_patch_vector.json
actinia_tiling_plugin/templates/patch/pc_strds_create.json
actinia_tiling_plugin/templates/patch/pc_strds_list_rasters.json
actinia_tiling_plugin/templates/patch/pc_vector_check_attrtable.json
actinia_tiling_plugin-1.2.0.dist-info/licenses/LICENSE.txt
actinia_tiling_plugin-1.2.0.dist-info/METADATA
actinia_tiling_plugin-1.2.0.dist-info/WHEEL
actinia_tiling_plugin-1.2.0.dist-info/top_level.txt
actinia_tiling_plugin-1.2.0.dist-info/RECORD
