Metadata-Version: 2.4
Name: actinia-tiling-plugin
Version: 1.2.0
Summary: An actinia-core plugin which adds tiling endpoints to actinia-core
Author: Anika Weinmann
Project-URL: Homepage, https://github.com/mundialis/actinia-tiling-plugin
Project-URL: Tutorial, https://mundialis.github.io/actinia_core
Project-URL: API_Docs, https://redocly.github.io/redoc/?url=https://actinia.mundialis.de/latest/swagger.json
Keywords: processing,earth observation,cloud-based processing,rest api,gis,grass gis,osgeo,tiling
Classifier: License :: OSI Approved :: GNU General Public License v3 or later (GPLv3+)
Classifier: Programming Language :: Python :: 3
Requires-Python: >=3.8
License-File: LICENSE.txt
Requires-Dist: actinia-grassdata-management-plugin
Requires-Dist: colorlog>=4.2.1
Provides-Extra: test
Requires-Dist: pytest; extra == "test"
Requires-Dist: pytest-cov; extra == "test"
Dynamic: license-file
